phunk/__init__.py
phunk/core.py
phunk/logging.py
phunk/miriade.py
phunk/models.py
phunk/plotting.py
space_phunk-0.1.3.dist-info/LICENSE
space_phunk-0.1.3.dist-info/METADATA
space_phunk-0.1.3.dist-info/WHEEL
space_phunk-0.1.3.dist-info/RECORD
