Metadata-Version: 2.1
Name: space-phunk
Version: 0.1.3
Summary: Fit photometric phase curves of asteroids.
Home-page: https://phunk.readthedocs.io/en/latest/
License: MIT
Author: Max Mahlke
Author-email: max.mahlke@oca.eu
Requires-Python: >=3.8
Classifier: License :: OSI Approved :: MIT License
Classifier: Programming Language :: Python :: 3
Classifier: Programming Language :: Python :: 3.8
Classifier: Programming Language :: Python :: 3.9
Classifier: Programming Language :: Python :: 3.10
Classifier: Programming Language :: Python :: 3.11
Classifier: Programming Language :: Python :: 3.12
Provides-Extra: docs
Requires-Dist: astropy (>=6.0)
Requires-Dist: lmfit (>=1.2.2)
Requires-Dist: matplotlib (>=3.4.3)
Requires-Dist: numpy (>=1.21) ; python_version >= "3.7" and python_version < "3.11"
Requires-Dist: numpy (>=1.24) ; python_version >= "3.11" and python_version < "4.0"
Requires-Dist: pandas (>=1.3.5)
Requires-Dist: requests (>=2.26.0,<3.0.0)
Requires-Dist: sbpy (>=0.3)
Requires-Dist: space-rocks (>=1.9)
Project-URL: Documentation, https://phunk.readthedocs.io/en/latest/
Project-URL: Repository, https://github.com/maxmahlke/phunk.git
